lighthousellm/__init__.py
lighthousellm/_expect.py
lighthousellm/_internal/__init__.py
lighthousellm/_internal/_aiter.py
lighthousellm/_internal/_background_thread.py
lighthousellm/_internal/_beta_decorator.py
lighthousellm/_internal/_compressed_traces.py
lighthousellm/_internal/_constants.py
lighthousellm/_internal/_edit_distance.py
lighthousellm/_internal/_embedding_distance.py
lighthousellm/_internal/_multipart.py
lighthousellm/_internal/_operations.py
lighthousellm/_internal/_orjson.py
lighthousellm/_internal/_patch.py
lighthousellm/_internal/_serde.py
lighthousellm/anonymizer.py
lighthousellm/async_client.py
lighthousellm/beta/__init__.py
lighthousellm/beta/_evals.py
lighthousellm/cli/README.md
lighthousellm/client.py
lighthousellm/env/__init__.py
lighthousellm/env/_git.py
lighthousellm/env/_runtime_env.py
lighthousellm/evaluation/__init__.py
lighthousellm/evaluation/_arunner.py
lighthousellm/evaluation/_name_generation.py
lighthousellm/evaluation/_runner.py
lighthousellm/evaluation/evaluator.py
lighthousellm/evaluation/integrations/__init__.py
lighthousellm/evaluation/integrations/_langchain.py
lighthousellm/evaluation/integrations/test.excalidraw.png
lighthousellm/evaluation/llm_evaluator.py
lighthousellm/evaluation/string_evaluator.py
lighthousellm/middleware.py
lighthousellm/py.typed
lighthousellm/pytest_plugin.py
lighthousellm/run_helpers.py
lighthousellm/run_trees.py
lighthousellm/schemas.py
lighthousellm/testing/__init__.py
lighthousellm/testing/_internal.py
lighthousellm/utils.py
lighthousellm/wrappers/__init__.py
lighthousellm/wrappers/_anthropic.py
lighthousellm/wrappers/_openai.py
lighthousellm-0.3.13.dist-info/entry_points.txt
lighthousellm-0.3.13.dist-info/METADATA
lighthousellm-0.3.13.dist-info/WHEEL
lighthousellm-0.3.13.dist-info/RECORD
